LICENSE
MANIFEST.in
README.rst
setup.py
admintheme/__init__.py
admintheme/models.py
admintheme/static/.DS_Store
admintheme/static/admin/.DS_Store
admintheme/static/admin/css/base.css
admintheme/static/admin/css/changelists.css
admintheme/static/admin/css/dashboard.css
admintheme/static/admin/css/forms.css
admintheme/static/admin/css/ie.css
admintheme/static/admin/css/login.css
admintheme/static/admin/css/print.css
admintheme/static/admin/css/screen.css
admintheme/static/admin/fonts/FontAwesome.otf
admintheme/static/admin/fonts/fontawesome-webfont.eot
admintheme/static/admin/fonts/fontawesome-webfont.svg
admintheme/static/admin/fonts/fontawesome-webfont.ttf
admintheme/static/admin/fonts/fontawesome-webfont.woff
admintheme/static/admin/img/.DS_Store
admintheme/static/admin/img/icon-unknown.gif
admintheme/static/admin/img/icon_addlink.gif
admintheme/static/admin/img/icon_searchbox.png
admintheme/static/admin/img/logo.png
admintheme/static/admin/img/selector-search.gif
admintheme/static/admin/js/.DS_Store
admintheme/static/admin/js/LICENSE-JQUERY.txt
admintheme/static/admin/js/SelectBox.js
admintheme/static/admin/js/SelectFilter2.js
admintheme/static/admin/js/actions.js
admintheme/static/admin/js/actions.min.js
admintheme/static/admin/js/calendar.js
admintheme/static/admin/js/collapse.js
admintheme/static/admin/js/collapse.min.js
admintheme/static/admin/js/compress.py
admintheme/static/admin/js/core.js
admintheme/static/admin/js/getElementsBySelector.js
admintheme/static/admin/js/inlines.js
admintheme/static/admin/js/inlines.min.js
admintheme/static/admin/js/jquery.init.js
admintheme/static/admin/js/jquery.js
admintheme/static/admin/js/jquery.min.js
admintheme/static/admin/js/prepopulate.js
admintheme/static/admin/js/prepopulate.min.js
admintheme/static/admin/js/timeparse.js
admintheme/static/admin/js/urlify.js
admintheme/static/admin/js/admin/DateTimeShortcuts.js
admintheme/static/admin/js/admin/RelatedObjectLookups.js
admintheme/static/admin/js/admin/ordering.js
django_admintheme.egg-info/PKG-INFO
django_admintheme.egg-info/SOURCES.txt
django_admintheme.egg-info/dependency_links.txt
django_admintheme.egg-info/top_level.txt
