Metadata-Version: 1.0
Name: django-admintheme
Version: 0.2
Summary: Django Admin Theme is a drop-in CSS replacement for the Django Admin app.
Home-page: https://github.com/callowayproject/django-admintheme
Author: Calloway Project
Author-email: webmaster@callowayproject.com
License: UNKNOWN
Platform: UNKNOWN
Classifier: License :: OSI Approved :: Apache Software License
Classifier: Framework :: Django
